item/__init__.py
item/cli.py
item/common.py
item/logging.yaml
item/py.typed
item/util.py
item/data/.git
item/data/.gitignore
item/data/README.md
item/data/item_config_example.yaml
item/data/structure.xml
item/data/historical/mapping_conv_phase1.yaml
item/data/historical/sources.yaml
item/data/model/models.yaml
item/data/model/regions.yaml
item/data/model/regions_item2.yaml
item/data/model/regions_roadmap.yaml
item/data/model/bp/regions.yaml
item/data/model/bp/scenarios.yaml
item/data/model/dimensions/fuel.yaml
item/data/model/dimensions/match.yaml
item/data/model/dimensions/mode.yaml
item/data/model/dimensions/technology.yaml
item/data/model/dimensions/variable.yaml
item/data/model/downscale/regions.yaml
item/data/model/downscale/regions_ipcc.yaml
item/data/model/downscale/regions_item2.yaml
item/data/model/downscale/regions_item3.yaml
item/data/model/eia/regions.yaml
item/data/model/eia/scenarios.yaml
item/data/model/eia/variables.yaml
item/data/model/eppa5/regions-base.yaml
item/data/model/eppa5/regions-gtap.yaml
item/data/model/eppa5/regions.yaml
item/data/model/eppa5/scenarios.yaml
item/data/model/eppa5/variables.yaml
item/data/model/eppa6/regions.yaml
item/data/model/exxonmobil/regions.yaml
item/data/model/exxonmobil/scenarios.yaml
item/data/model/gcam/regions.yaml
item/data/model/gcam/scenarios.yaml
item/data/model/get/regions.yaml
item/data/model/get/scenarios.yaml
item/data/model/itf/regions.yaml
item/data/model/itf/scenarios.yaml
item/data/model/message/regions.yaml
item/data/model/message/scenarios.yaml
item/data/model/momo/regions.yaml
item/data/model/momo/scenarios.yaml
item/data/model/roadmap/regions.yaml
item/data/model/roadmap/scenarios.yaml
item/data/model/shell/regions.yaml
item/data/model/shell/scenarios.yaml
item/data/model/statoil/regions.yaml
item/data/model/statoil/scenarios.yaml
item/historical/T000.py
item/historical/T001.py
item/historical/T002.py
item/historical/T003.py
item/historical/T004.py
item/historical/T005.py
transport_energy-2025.3.31.dist-info/METADATA
transport_energy-2025.3.31.dist-info/WHEEL
transport_energy-2025.3.31.dist-info/entry_points.txt
transport_energy-2025.3.31.dist-info/licenses/LICENSE
transport_energy-2025.3.31.dist-info/RECORD
