Metadata-Version: 2.4
Name: transport-energy
Version: 2025.3.31
Project-URL: Homepage, https://github.com/transportenergy/database
Project-URL: Documentation, https://transportenergy.readthedocs.io
Author-email: International Transport Energy Modeling contributors <mail@transportenergy.org>
Maintainer-email: Paul Natsuo Kishimoto <mail@paul.kishimoto.name>
License-File: LICENSE
Classifier: Development Status :: 4 - Beta
Classifier: Intended Audience :: Science/Research
Classifier: Operating System :: OS Independent
Classifier: Programming Language :: Python
Classifier: Programming Language :: Python :: 3
Classifier: Programming Language :: Python :: 3.9
Classifier: Programming Language :: Python :: 3.10
Classifier: Programming Language :: Python :: 3.11
Classifier: Programming Language :: Python :: 3.12
Classifier: Programming Language :: Python :: 3.13
Classifier: Topic :: Scientific/Engineering
Requires-Python: >=3.9
Requires-Dist: click
Requires-Dist: iam-units
Requires-Dist: openpyxl
Requires-Dist: pandas
Requires-Dist: pint
Requires-Dist: plotnine
Requires-Dist: pycountry
Requires-Dist: pyyaml
Requires-Dist: sdmx1>=2.8.0
Requires-Dist: xarray
Provides-Extra: doc
Requires-Dist: furo; extra == 'doc'
Requires-Dist: sphinx; extra == 'doc'
Provides-Extra: eppa
Requires-Dist: gdx>=3; extra == 'eppa'
Provides-Extra: hist
Requires-Dist: jinja2; extra == 'hist'
Requires-Dist: requests; extra == 'hist'
Provides-Extra: tests
Requires-Dist: furo; extra == 'tests'
Requires-Dist: jinja2; extra == 'tests'
Requires-Dist: pytest; extra == 'tests'
Requires-Dist: pytest-cov; extra == 'tests'
Requires-Dist: requests; extra == 'tests'
Requires-Dist: sphinx; extra == 'tests'
